[
    { "name": "Aftonfalk" },
    { "name": "Alfågel" },
    { "name": "Alförrädare" },
    { "name": "Alkekung" },
    { "name": "Alpjärnsparv" },
    { "name": "Alpkaja" },
    { "name": "Alpkråka" },
    { "name": "Alpseglare" },
    { "name": "Amerikansk kopparand" },
    { "name": "Backsvala" },
    { "name": "Balkanhök" },
    { "name": "Balkanmes" },
    { "name": "Balkanspett" },
    { "name": "Bergand" },
    { "name": "Bergfink" },
    { "name": "Berghöna" },
    { "name": "Berglärka" },
    { "name": "Bergsångare" },
    { "name": "Berguv" },
    { "name": "Bivråk" },
    { "name": "Biätare" },
    { "name": "Björktrast" },
    { "name": "Blektornseglare" },
    { "name": "Blå kärrhök" },
    { "name": "Blåhake" },
    { "name": "Blåkråka" },
    { "name": "Blåmes" },
    { "name": "Blåskata" },
    { "name": "Blåtrast" },
    { "name": "Bläsand" },
    { "name": "Bläsgås" },
    { "name": "Bofink" },
    { "name": "Brandkronad kungsfågel" },
    { "name": "Brednäbbad simsnäppa" },
    { "name": "Bredstjärtad labb" },
    { "name": "Bronsibis" },
    { "name": "Brun kärrhök" },
    { "name": "Brunand" },
    { "name": "Brunglada" },
    { "name": "Brushane" },
    { "name": "Buskskvätta" },
    { "name": "Busksångare" },
    { "name": "Bändelkorsnäbb" },
    { "name": "Cettisångare" },
    { "name": "Citronsiska" },
    { "name": "Citronärla" },
    { "name": "Dalripa" },
    { "name": "Dammsnäppa" },
    { "name": "Diamantfasan" },
    { "name": "Domherre" },
    { "name": "Drillsnäppa" },
    { "name": "Dubbelbeckasin" },
    { "name": "Dubbeltrast" },
    { "name": "Duvhök" },
    { "name": "Dvärglira" },
    { "name": "Dvärgbeckasin" },
    { "name": "Dvärglärka" },
    { "name": "Dvärgmås" },
    { "name": "Dvärgrördrom" },
    { "name": "Dvärgskarv" },
    { "name": "Dvärgsparv" },
    { "name": "Dvärgsumphöna" },
    { "name": "Dvärguv" },
    { "name": "Dvärgörn" },
    { "name": "Ejder" },
    { "name": "Eksångare" },
    { "name": "Eleonorafalk" },
    { "name": "Enkelbeckasin" },
    { "name": "Entita" },
    { "name": "Fasan" },
    { "name": "Fiskgjuse" },
    { "name": "Fiskmås" },
    { "name": "Fisktärna" },
    { "name": "Fjällabb" },
    { "name": "Fjällgås" },
    { "name": "Fjällpipare" },
    { "name": "Fjällripa" },
    { "name": "Fjälluggla" },
    { "name": "Fjällvråk" },
    { "name": "Flamingo" },
    { "name": "Flodsångare" },
    { "name": "Forsärla" },
    { "name": "Fältpiplärka" },
    { "name": "Glasögonsångare" },
    { "name": "Gluttsnäppa" },
    { "name": "Gransångare" },
    { "name": "Gravand" },
    { "name": "Grå flugsnappare" },
    { "name": "Grågam" },
    { "name": "Grågås" },
    { "name": "Gråhakedopping" },
    { "name": "Gråkråka" },
    { "name": "Grålira" },
    { "name": "Gråsiska" },
    { "name": "Gråsparv" },
    { "name": "Gråspett" },
    { "name": "Gråtrut" },
    { "name": "Gräsand" },
    { "name": "Gräshoppsångare" },
    { "name": "Grässångare" },
    { "name": "Grönbena" },
    { "name": "Grönfink" },
    { "name": "Gröngöling" },
    { "name": "Grönsiska" },
    { "name": "Grönsångare" },
    { "name": "Guldfasan" },
    { "name": "Gulhämpling" },
    { "name": "Gulnäbbad lira" },
    { "name": "Gulsparv" },
    { "name": "Gulärla" },
    { "name": "Gyllensparv" },
    { "name": "Gåsgam" },
    { "name": "Gärdsmyg" },
    { "name": "Gök" },
    { "name": "Göktyta" },
    { "name": "Halsbandsflugsnappare" },
    { "name": "Halsbandsparakit" },
    { "name": "Havslöpare" },
    { "name": "Havssula" },
    { "name": "Havstrut" },
    { "name": "Havsörn" },
    { "name": "Hornuggla" },
    { "name": "Hussvala" },
    { "name": "Häcksparv" },
    { "name": "Häger" },
    { "name": "Hämpling" },
    { "name": "Härfågel" },
    { "name": "Härmsångare" },
    { "name": "Höksångare" },
    { "name": "Hökuggla" },
    { "name": "Hökörn" },
    { "name": "Iltärna" },
    { "name": "Islandsknipa" },
    { "name": "Islom" },
    { "name": "Jaktfalk" },
    { "name": "Jorduggla" },
    { "name": "Järnsparv" },
    { "name": "Järpe" },
    { "name": "Kaja" },
    { "name": "Kalenderlärka" },
    { "name": "Kamsothöna" },
    { "name": "Kanadagås" },
    { "name": "Kattuggla" },
    { "name": "Kaveldunssångare" },
    { "name": "Kejsarörn" },
    { "name": "Kentsk tärna" },
    { "name": "Klippduva" },
    { "name": "Klipphöna" },
    { "name": "Klippnötväcka" },
    { "name": "Klippsparv" },
    { "name": "Klippsvala" },
    { "name": "Klykstjärtad stormsvala" },
    { "name": "Knipa" },
    { "name": "Knölsvan" },
    { "name": "Kohäger" },
    { "name": "Koltrast" },
    { "name": "Kopparand" },
    { "name": "Kornknarr" },
    { "name": "Kornsparv" },
    { "name": "Korp" },
    { "name": "Korsikansk nötväcka" },
    { "name": "Korttålärka" },
    { "name": "Kricka" },
    { "name": "Krushuvad pelikan" },
    { "name": "Kungsfiskare" },
    { "name": "Kungsfågel" },
    { "name": "Kungsörn" },
    { "name": "Kustpipare" },
    { "name": "Kustsnäppa" },
    { "name": "Kärrsnäppa" },
    { "name": "Kärrsångare" },
    { "name": "Labb" },
    { "name": "Ladusvala" },
    { "name": "Lagerlärka" },
    { "name": "Lammgam" },
    { "name": "Lappmes" },
    { "name": "Lappsparv" },
    { "name": "Lappuggla" },
    { "name": "Lavskrika" },
    { "name": "Ljungpipare" },
    { "name": "Lundsångare" },
    { "name": "Lunnefågel" },
    { "name": "Långnäbbad mås" },
    { "name": "Lärkfalk" },
    { "name": "Lövsångare" },
    { "name": "Madeirapetrell" },
    { "name": "Mandarinand" },
    { "name": "Marmorand" },
    { "name": "Masktörnskata" },
    { "name": "Medelhavsstenskvätta" },
    { "name": "Mellanspett" },
    { "name": "Mindre flugsnappare" },
    { "name": "Mindre hackspett" },
    { "name": "Mindre korsnäbb" },
    { "name": "Mindre lira" },
    { "name": "Mindre skrikörn" },
    { "name": "Mindre strandpipare" },
    { "name": "Mindre sumphöna" },
    { "name": "Mindre sångsvan" },
    { "name": "Minervauggla" },
    { "name": "Morkulla" },
    { "name": "Mosnäppa" },
    { "name": "Murkrypare" },
    { "name": "Myrsnäppa" },
    { "name": "Myrspov" },
    { "name": "Mästersångare" },
    { "name": "Natthäger" },
    { "name": "Nattskärra" },
    { "name": "Nilgås" },
    { "name": "Nordsångare" },
    { "name": "Näktergal" },
    { "name": "Nötkråka" },
    { "name": "Nötskrika" },
    { "name": "Nötväcka" },
    { "name": "Olivsångare" },
    { "name": "Ormvråk" },
    { "name": "Ormörn" },
    { "name": "Orre" },
    { "name": "Ortolansparv" },
    { "name": "Pelikan" },
    { "name": "Pilfink" },
    { "name": "Pilgrimsfalk" },
    { "name": "Polygottsångare" },
    { "name": "Provencesångare" },
    { "name": "Prutgås" },
    { "name": "Pungmes" },
    { "name": "Purpurhäger" },
    { "name": "Purpurhöna" },
    { "name": "Pärluggla" },
    { "name": "Rallhäger" },
    { "name": "Rapphöna" },
    { "name": "Ringduva" },
    { "name": "Ringnäbbad mås" },
    { "name": "Ringtrast" },
    { "name": "Rosenfink" },
    { "name": "Rosenstare" },
    { "name": "Rosentärna" },
    { "name": "Roskarl" },
    { "name": "Rostand" },
    { "name": "Rostgumpsvala" },
    { "name": "Rostsparv" },
    { "name": "Råka" },
    { "name": "Röd glada" },
    { "name": "Rödbena" },
    { "name": "Rödfalk" },
    { "name": "Rödhake" },
    { "name": "Rödhalsad gås" },
    { "name": "Rödhalsad nattskärra" },
    { "name": "Rödhuvad dykand" },
    { "name": "Rödhuvad törnskata" },
    { "name": "Rödhöna" },
    { "name": "Rödnäbbad trut" },
    { "name": "Rödspov" },
    { "name": "Rödstjärt" },
    { "name": "Rödstrupig piplärka" },
    { "name": "Rödstrupig sångare" },
    { "name": "Rödvingetrast" },
    { "name": "Rördrom" },
    { "name": "Rörhöna" },
    { "name": "Rörsångare" },
    { "name": "Salskrake" },
    { "name": "Sammetshätta" },
    { "name": "Sandlöpare" },
    { "name": "Sandtärna" },
    { "name": "Sardinsksångare" },
    { "name": "Sidensvans" },
    { "name": "Silkeshäger" },
    { "name": "Sillgrissla" },
    { "name": "Silltrut" },
    { "name": "Silvertärna" },
    { "name": "Sjöorre" },
    { "name": "Skata" },
    { "name": "Skatgök" },
    { "name": "Skedand" },
    { "name": "Skedstork" },
    { "name": "Skogsduva" },
    { "name": "Skogssnäppa" },
    { "name": "Skotsk korsnäbb" },
    { "name": "Skrattmås" },
    { "name": "Skräntärna" },
    { "name": "Skäggdopping" },
    { "name": "Skäggmes" },
    { "name": "Skäggtärna" },
    { "name": "Skärfläcka" },
    { "name": "Skärpiplärka" },
    { "name": "Skärsnäppa" },
    { "name": "Slagfalk" },
    { "name": "Slaguggla" },
    { "name": "Smalnäbbad simsnäppa" },
    { "name": "Smutsgam" },
    { "name": "Smådopping" },
    { "name": "Småfläckig sumphöna" },
    { "name": "Smålom" },
    { "name": "Småskrake" },
    { "name": "Småsnäppa" },
    { "name": "Småspov" },
    { "name": "Småtrapp" },
    { "name": "Småtärna" },
    { "name": "Snatterand" },
    { "name": "Snöfink" },
    { "name": "Snösiska" },
    { "name": "Snösparv" },
    { "name": "Sommargylling" },
    { "name": "Sothöna" },
    { "name": "Spansk sparv" },
    { "name": "Sparvhök" },
    { "name": "Sparvuggla" },
    { "name": "Spetsbergsgrissla" },
    { "name": "Spetsbergsgås" },
    { "name": "Spillkråka" },
    { "name": "Sporrvipa" },
    { "name": "Spovsnäppa" },
    { "name": "Stare" },
    { "name": "Steglits" },
    { "name": "Stenfalk" },
    { "name": "Stenhöna" },
    { "name": "Stenknäck" },
    { "name": "Stenskvätta" },
    { "name": "Stensparv" },
    { "name": "Stentrast" },
    { "name": "Stjärtand" },
    { "name": "Stjärtmes" },
    { "name": "Storlabb" },
    { "name": "Storlom" },
    { "name": "Stormfågel" },
    { "name": "Stormsvala" },
    { "name": "Storskarv" },
    { "name": "Storskrake" },
    { "name": "Storspov" },
    { "name": "Stortrapp" },
    { "name": "Strandskata" },
    { "name": "Strömand" },
    { "name": "Strömstare" },
    { "name": "Styltlöpare" },
    { "name": "Stäpphök" },
    { "name": "Större hackspett" },
    { "name": "Större korsnäbb" },
    { "name": "Större lira" },
    { "name": "Större skrikörn" },
    { "name": "Större strandpipare" },
    { "name": "Svart stare" },
    { "name": "Svart stenskvätta" },
    { "name": "Svart stork" },
    { "name": "Svartbent strandpipare" },
    { "name": "Svartbukig flyghöna" },
    { "name": "Svarthakad buskskvätta" },
    { "name": "Svarthakedopping" },
    { "name": "Svarthalsad dopping" },
    { "name": "Svarthuvad sparv" },
    { "name": "Svarthuvad mås" },
    { "name": "Svarthätta" },
    { "name": "Svartmes" },
    { "name": "Svartpannad törnskata" },
    { "name": "Svartrödstjärt" },
    { "name": "Svartsnäppa" },
    { "name": "Svarttärna" },
    { "name": "Svartvingad glada" },
    { "name": "Svartvit flugsnappare" },
    { "name": "Svärta" },
    { "name": "Sydnäcktergal" },
    { "name": "Sånglärka" },
    { "name": "Sångsvan" },
    { "name": "Sädesärla" },
    { "name": "Sädgås" },
    { "name": "Sävsparv" },
    { "name": "Sävsångare" },
    { "name": "Taigasångare" },
    { "name": "Talgoxe" },
    { "name": "Tallbit" },
    { "name": "Talltita" },
    { "name": "Taltrast" },
    { "name": "Tamduva" },
    { "name": "Tatarfalk" },
    { "name": "Tereksnäppa" },
    { "name": "Tjockfot" },
    { "name": "Tjäder" },
    { "name": "Tobisgrissla" },
    { "name": "Tofslärka" },
    { "name": "Tofsmes" },
    { "name": "Tofsvipa" },
    { "name": "Toppskarv" },
    { "name": "Tordmule" },
    { "name": "Tornfalk" },
    { "name": "Tornseglare" },
    { "name": "Tornuggla" },
    { "name": "Trana" },
    { "name": "Trastsångare" },
    { "name": "Tretåig hackspett" },
    { "name": "Tretåig mås" },
    { "name": "Trädgårdssångare" },
    { "name": "Trädgårdsträdkrypare" },
    { "name": "Trädkrypare" },
    { "name": "Trädlärka" },
    { "name": "Trädmås" },
    { "name": "Trädnäcktergal" },
    { "name": "Trädpiplärka" },
    { "name": "Turkduva" },
    { "name": "Turturduva" },
    { "name": "Tuvsnäppa" },
    { "name": "Tärnmås" },
    { "name": "Törnskata" },
    { "name": "Törnsångare" },
    { "name": "Vadarsvala" },
    { "name": "Vaktel" },
    { "name": "Varfågel" },
    { "name": "Vassångare" },
    { "name": "Vattenpiplärka" },
    { "name": "Vattenrall" },
    { "name": "Vattensångare" },
    { "name": "Videsparv" },
    { "name": "Vigg" },
    { "name": "Vinterhämpling" },
    { "name": "Vit stork" },
    { "name": "Vitbukig flyghöna" },
    { "name": "Vitkindad gås" },
    { "name": "Vitnäbbad islom" },
    { "name": "Vitryggig hackspett" },
    { "name": "Vittrut" },
    { "name": "Vitvingad tärna" },
    { "name": "Vitvingad trut" },
    { "name": "Vitögd dykand" },
    { "name": "Wilsonsimsnäppa" },
    { "name": "Årta" },
    { "name": "Ägretthäger" },
    { "name": "Ängshök" },
    { "name": "Ängspiplärka" },
    { "name": "Ärtsångare" },
    { "name": "Örnvråk" }
]